pt_pump_up_orms/ORM.py
pt_pump_up_orms/__init__.py
pt_pump_up_orms/exception/HTTPException.py
pt_pump_up_orms/exception/__init__.py
pt_pump_up_orms/orms/Author.py
pt_pump_up_orms/orms/Dataset.py
pt_pump_up_orms/orms/Link.py
pt_pump_up_orms/orms/Model.py
pt_pump_up_orms/orms/NLP_Task.py
pt_pump_up_orms/orms/ResourceStats.py
pt_pump_up_orms/orms/Result.py
pt_pump_up_orms/orms/__init__.py
pt_pump_up_orms-0.0.18.dist-info/METADATA
pt_pump_up_orms-0.0.18.dist-info/WHEEL
pt_pump_up_orms-0.0.18.dist-info/top_level.txt
pt_pump_up_orms-0.0.18.dist-info/RECORD
